imohash_rs-0.2.0.dist-info/METADATA
imohash_rs-0.2.0.dist-info/WHEEL
imohash_rs.libs/libgcc_s-5b5488a6.so.1
imohash_rs/__init__.py
imohash_rs/__main__.py
imohash_rs/__init__.pyi
imohash_rs/imohash_rs.cpython-313t-arm-linux-musleabihf.so
imohash_rs-0.2.0.dist-info/RECORD
