Metadata-Version: 2.4
Name: imohash_rs
Version: 0.2.0
Summary: Fast hashing for large files
Keywords: checksum,digest,hash,murmur3,encoding
Author: Михаил Драгункин <contact@md.land>
Author-email: Михаил Драгункин <contact@md.land>
License: MIT
Project-URL: Source Code, https://github.com/unsektor/py-imohash
